{
  "extractor_name": "structured_data",
  "data": {
    "json_ld": [],
    "nodes": [],
    "microdata": [],
    "opengraph": {
      "og:title": "Home | Reds Residential and Restaurant Construction",
      "og:url": "https://www.redsrrc.com/home-1",
      "og:site_name": "Reds Residential and",
      "og:type": "website"
    },
    "schema_types": [],
    "types": [],
    "has_structured_data": true
  },
  "warnings": [],
  "errors": [],
  "source_references": [
    "pages/3d4bed22e1184b72/rendered-dom.html"
  ]
}